pysstv/__init__.py
pysstv/__main__.py
pysstv/color.py
pysstv/grayscale.py
pysstv/sstv.py
pysstv/examples/__init__.py
pysstv/examples/codegen.py
pysstv/examples/get_floats.py
pysstv/examples/get_freq_bits.py
pysstv/examples/gimp-plugin.py
pysstv/examples/overlay.py
pysstv/examples/pyaudio_sstv.py
pysstv/examples/repeater.py
pysstv/tests/__init__.py
pysstv/tests/common.py
pysstv/tests/test_color.py
pysstv/tests/test_sstv.py
PySSTV-0.5.5.dist-info/LICENSE.txt
PySSTV-0.5.5.dist-info/METADATA
PySSTV-0.5.5.dist-info/WHEEL
PySSTV-0.5.5.dist-info/entry_points.txt
PySSTV-0.5.5.dist-info/top_level.txt
PySSTV-0.5.5.dist-info/RECORD
