Metadata-Version: 2.1
Name: PySSTV
Version: 0.5.5
Summary: Python classes for generating Slow-scan Television transmissions
Home-page: https://github.com/dnet/pySSTV
Author: András Veres-Szentkirályi
Author-email: vsza@vsza.hu
License: MIT
Keywords: HAM SSTV slow-scan television Scottie Martin Robot Pasokon
Classifier: Development Status :: 4 - Beta
Classifier: Topic :: Communications :: Ham Radio
Classifier: Topic :: Multimedia :: Video :: Conversion
Classifier: License :: OSI Approved :: MIT License
Classifier: Operating System :: OS Independent
License-File: LICENSE.txt
Requires-Dist: Pillow
